[
  {
    "id": "18344062750170278",
    "timestamp": "2026-06-23T20:53:14+0000",
    "media_type": "CAROUSEL_ALBUM",
    "caption_preview": "Termo Bíblico do dia",
    "permalink": "https://www.instagram.com/p/DZ8Uf32GDub/",
    "like_count": 0,
    "comments_count": 0,
    "insights": {
      "reach": 0,
      "saved": 0,
      "shares": 0,
      "total_interactions": 0
    },
    "collected_at": "2026-06-23"
  },
  {
    "id": "17958874446130792",
    "timestamp": "2026-06-23T20:45:33+0000",
    "media_type": "CAROUSEL_ALBUM",
    "caption_preview": "Gratidão diária",
    "permalink": "https://www.instagram.com/p/DZ8Tnr9mk5M/",
    "like_count": 0,
    "comments_count": 0,
    "insights": {
      "reach": 0,
      "saved": 0,
      "shares": 0,
      "total_interactions": 0
    },
    "collected_at": "2026-06-23"
  }
]